{
  "project_info": {
    "project_number": "310072836706",
    "project_id": "holynicmobileapp",
    "storage_bucket": "holynicmobileapp.appspot.com"
  },
  "client": [
    {
      "client_info": {
        "mobilesdk_app_id": "1:310072836706:android:5a907b424fcbd2a901873b",
        "android_client_info": {
          "package_name": "com.holydev.holynicmobileapp"
        }
      },
      "oauth_client": [
        {
          "client_id": "310072836706-hakr9k9uj3r8qjshijdvl4e2ica7af8b.apps.googleusercontent.com",
          "client_type": 3
        }
      ],
      "api_key": [
        {
          "current_key": "AIzaSyBVoPOnMZG7ue7_F_mz3EN8VMMIfPExxVs"
        }
      ],
      "services": {
        "appinvite_service": {
          "other_platform_oauth_client": [
            {
              "client_id": "310072836706-hakr9k9uj3r8qjshijdvl4e2ica7af8b.apps.googleusercontent.com",
              "client_type": 3
            }
          ]
        }
      }
    }
  ],
  "configuration_version": "1"
}